get_retries/__init__.py
get_retries/get.py
get_retries-0.1.1.dist-info/LICENSE
get_retries-0.1.1.dist-info/METADATA
get_retries-0.1.1.dist-info/WHEEL
get_retries-0.1.1.dist-info/top_level.txt
get_retries-0.1.1.dist-info/RECORD
