Metadata-Version: 2.1
Name: get-retries
Version: 0.1.1
Summary: Adding retries to Requests.get() with exponential backoff
Home-page: https://github.com/jfilter/get_retries
Author: Johannes Filter
Author-email: hi@jfilter.de
License: MIT
Platform: UNKNOWN
Classifier: Programming Language :: Python :: 3.5
Classifier: Programming Language :: Python :: 3.6
Classifier: Programming Language :: Python :: 3.7
Classifier: License :: OSI Approved :: MIT License
Requires-Dist: requests
